cpp_source_extractor/__init__.py
cpp_source_extractor/extractor.py
tests/__init__.py
tests/test_extractor.py
cpp_source_extractor-0.1.dist-info/LICENSE
cpp_source_extractor-0.1.dist-info/METADATA
cpp_source_extractor-0.1.dist-info/WHEEL
cpp_source_extractor-0.1.dist-info/top_level.txt
cpp_source_extractor-0.1.dist-info/RECORD
