Metadata-Version: 2.1
Name: cpp_source_extractor
Version: 0.1
Summary: A python library for extracting C++ function implementations from source code
Home-page: https://github.com/whexy/cpp_source_extractor
Author: Wenxuan Shi
Author-email: wenxuan.shi@northwestern.edu
Classifier: Programming Language :: Python :: 3
Classifier: License :: OSI Approved :: MIT License
License-File: LICENSE
Requires-Dist: libclang
